rss2socials/__init__.py
rss2socials/__main__.py
rss2socials/cli.py
rss2socials/common/metadata.py
rss2socials/common/openai_utils.py
rss2socials/common/rss_utils.py
rss2socials/connector/__init__.py
rss2socials/connector/bluesky.py
rss2socials-1.1.21.dist-info/licenses/LICENSE
rss2socials-1.1.21.dist-info/METADATA
rss2socials-1.1.21.dist-info/WHEEL
rss2socials-1.1.21.dist-info/entry_points.txt
rss2socials-1.1.21.dist-info/top_level.txt
rss2socials-1.1.21.dist-info/RECORD
