Metadata-Version: 2.4
Name: rss2socials
Version: 1.1.21
Summary: Modular Python CLI tool to automatically post new entries from an RSS or Atom feed to one or more social media platforms. Easily extensible, robust, and safe for automation and CI/CD workflows.
Author-email: "Jeremy T. Bouse" <Jeremy.Bouse@UnderGrid.net>
License-Expression: MIT
Project-URL: Homepage, https://github.com/ugns/rss2socials
Project-URL: Repository, https://github.com/ugns/rss2socials
Project-URL: Issues, https://github.com/ugns/rss2socials/issues
Project-URL: Changelog, https://github.com/ugns/rss2socials/blob/main/CHANGELOG.md
Classifier: Development Status :: 4 - Beta
Classifier: Programming Language :: Python :: 3
Classifier: Programming Language :: Python :: 3.8
Classifier: Programming Language :: Python :: 3.9
Classifier: Programming Language :: Python :: 3.10
Classifier: Programming Language :: Python :: 3.11
Classifier: Programming Language :: Python :: 3.12
Classifier: Programming Language :: Python :: 3.13
Classifier: Topic :: Utilities
Classifier: Environment :: Console
Requires-Python: >=3.9
License-File: LICENSE
Requires-Dist: atproto==0.0.62
Requires-Dist: feedparser==6.0.11
Requires-Dist: grapheme==0.6.0
Requires-Dist: lxml<6.0.0,>=5.3.0
Requires-Dist: lxml_html_clean==0.4.2
Requires-Dist: openai==1.102.0
Requires-Dist: python-dotenv==1.1.1
Requires-Dist: requests==2.32.5
Requires-Dist: trafilatura==2.0.0
Provides-Extra: dev
Requires-Dist: build; extra == "dev"
Requires-Dist: coverage; extra == "dev"
Requires-Dist: flake8; extra == "dev"
Requires-Dist: importlib_metadata; extra == "dev"
Requires-Dist: pytest; extra == "dev"
Requires-Dist: python-semantic-release; extra == "dev"
Requires-Dist: tox; extra == "dev"
Requires-Dist: twine; extra == "dev"
Dynamic: license-file
